{
  "repo_name": "QuantumA/FATE",
  "stars": 3787,
  "license": [
    "Apache-2.0"
  ],
  "first_star_date": null,
  "total_files": 5,
  "files": [
    {
      "file": "homo_lr_base.py",
      "original_path": "python/federatedml/linear_model/logistic_regression/homo_logistic_regression/homo_lr_base.py",
      "size": 6314,
      "alphanum_fraction": 0.6604371239,
      "line_count": 139,
      "character_count": 6314
    },
    {
      "file": "engine_utils.py",
      "original_path": "python/fate_arch/common/engine_utils.py",
      "size": 4582,
      "alphanum_fraction": 0.715626364,
      "line_count": 112,
      "character_count": 4582
    },
    {
      "file": "gmpy_math.py",
      "original_path": "python/federatedml/secureprotol/gmpy_math.py",
      "size": 2784,
      "alphanum_fraction": 0.5308908046,
      "line_count": 134,
      "character_count": 2784
    },
    {
      "file": "pipeline-hetero-feature-selection-multi-iso.py",
      "original_path": "examples/pipeline/hetero_feature_selection/pipeline-hetero-feature-selection-multi-iso.py",
      "size": 4366,
      "alphanum_fraction": 0.5515345854,
      "line_count": 141,
      "character_count": 4366
    },
    {
      "file": "pipeline_train_manually_lr.py",
      "original_path": "examples/experiment_template/pipeline/hetero_lr/pipeline_train_manually_lr.py",
      "size": 8485,
      "alphanum_fraction": 0.6796700059,
      "line_count": 208,
      "character_count": 8485
    }
  ]
}