{
  "repo_name": "yihui-he2020/epipolar-transformers",
  "stars": 360,
  "license": [
    "MIT"
  ],
  "first_star_date": null,
  "total_files": 5,
  "files": [
    {
      "file": "resnet.py",
      "original_path": "modeling/backbones/resnet.py",
      "size": 19859,
      "alphanum_fraction": 0.599375598,
      "line_count": 519,
      "character_count": 19859
    },
    {
      "file": "triangulation.py",
      "original_path": "vision/triangulation.py",
      "size": 15926,
      "alphanum_fraction": 0.553874168,
      "line_count": 450,
      "character_count": 15926
    },
    {
      "file": "joints_dataset.py",
      "original_path": "data/datasets/joints_dataset.py",
      "size": 20930,
      "alphanum_fraction": 0.5271380793,
      "line_count": 489,
      "character_count": 20930
    },
    {
      "file": "oracle.py",
      "original_path": "modeling/layers/oracle.py",
      "size": 6579,
      "alphanum_fraction": 0.5602675179,
      "line_count": 165,
      "character_count": 6579
    },
    {
      "file": "multiview_mpii.py",
      "original_path": "data/datasets/multiview_mpii.py",
      "size": 3388,
      "alphanum_fraction": 0.4808146399,
      "line_count": 115,
      "character_count": 3388
    }
  ]
}