{
  "repo_name": "tre3x/awesomeScripts",
  "stars": 245,
  "license": [
    "MIT"
  ],
  "first_star_date": null,
  "total_files": 5,
  "files": [
    {
      "file": "website_cloner.py",
      "original_path": "website_cloner/website_cloner.py",
      "size": 2076,
      "alphanum_fraction": 0.5606936416,
      "line_count": 70,
      "character_count": 2076
    },
    {
      "file": "cartoonifier.py",
      "original_path": "cartoonifier/cartoonifier.py",
      "size": 2124,
      "alphanum_fraction": 0.6869114878,
      "line_count": 65,
      "character_count": 2124
    },
    {
      "file": "torrent_to_google_drive_downloader.py",
      "original_path": "torrent to Google Drive Downloader/torrent_to_google_drive_downloader.py",
      "size": 2696,
      "alphanum_fraction": 0.634272997,
      "line_count": 101,
      "character_count": 2696
    },
    {
      "file": "countries_trivia.py",
      "original_path": "countries_trivia_game/countries_trivia.py",
      "size": 2989,
      "alphanum_fraction": 0.5496821679,
      "line_count": 96,
      "character_count": 2989
    },
    {
      "file": "sorting_visulaizer.py",
      "original_path": "sorting_visualizer/sorting_visulaizer.py",
      "size": 2063,
      "alphanum_fraction": 0.6136694135,
      "line_count": 82,
      "character_count": 2063
    }
  ]
}