{
  "repo_name": "wanghm92/graph-2-text",
  "stars": 149,
  "license": [
    "MIT"
  ],
  "first_star_date": null,
  "total_files": 5,
  "files": [
    {
      "file": "jsonrpc.py",
      "original_path": "utils/jsonrpc.py",
      "size": 43486,
      "alphanum_fraction": 0.5771282712,
      "line_count": 1077,
      "character_count": 43486
    },
    {
      "file": "sr_onmtgcn_deanonymise.py",
      "original_path": "srtask/sr_onmtgcn_deanonymise.py",
      "size": 2362,
      "alphanum_fraction": 0.5922946655,
      "line_count": 70,
      "character_count": 2362
    },
    {
      "file": "sr11_linear_input.py",
      "original_path": "srtask/sr11_linear_input.py",
      "size": 3763,
      "alphanum_fraction": 0.5543449375,
      "line_count": 103,
      "character_count": 3763
    },
    {
      "file": "metrics.py",
      "original_path": "webnlg_eval_scripts/metrics.py",
      "size": 2956,
      "alphanum_fraction": 0.6146820027,
      "line_count": 73,
      "character_count": 2956
    },
    {
      "file": "GlobalAttention.py",
      "original_path": "onmt/modules/GlobalAttention.py",
      "size": 7000,
      "alphanum_fraction": 0.5595714286,
      "line_count": 214,
      "character_count": 7000
    }
  ]
}