{
  "repo_name": "CosmosHua/Deformable-ConvNets",
  "stars": 3976,
  "license": [
    "MIT"
  ],
  "first_star_date": null,
  "total_files": 5,
  "files": [
    {
      "file": "fpn_roi_pooling.py",
      "original_path": "fpn/operator_py/fpn_roi_pooling.py",
      "size": 8305,
      "alphanum_fraction": 0.5936183022,
      "line_count": 147,
      "character_count": 8305
    },
    {
      "file": "rcnn.py",
      "original_path": "fpn/core/rcnn.py",
      "size": 7414,
      "alphanum_fraction": 0.6645535473,
      "line_count": 191,
      "character_count": 7414
    },
    {
      "file": "resnet_v1_101_fpn_dcn_rcnn.py",
      "original_path": "fpn/symbols/resnet_v1_101_fpn_dcn_rcnn.py",
      "size": 86614,
      "alphanum_fraction": 0.6165977787,
      "line_count": 1011,
      "character_count": 86614
    },
    {
      "file": "train_rcnn.py",
      "original_path": "faster_rcnn/function/train_rcnn.py",
      "size": 5829,
      "alphanum_fraction": 0.6778178075,
      "line_count": 141,
      "character_count": 5829
    },
    {
      "file": "proposal_target.py",
      "original_path": "rfcn/operator_py/proposal_target.py",
      "size": 4712,
      "alphanum_fraction": 0.6326400679,
      "line_count": 121,
      "character_count": 4712
    }
  ]
}