{
  "repo_name": "RLGraph/RLGraph",
  "stars": 290,
  "license": [
    "Apache-2.0"
  ],
  "first_star_date": null,
  "total_files": 5,
  "files": [
    {
      "file": "__init__.py",
      "original_path": "rlgraph/components/memories/__init__.py",
      "size": 2283,
      "alphanum_fraction": 0.741130092,
      "line_count": 57,
      "character_count": 2283
    },
    {
      "file": "decorators.py",
      "original_path": "rlgraph/utils/decorators.py",
      "size": 38832,
      "alphanum_fraction": 0.6542542233,
      "line_count": 705,
      "character_count": 38832
    },
    {
      "file": "test_base_agent_functionality.py",
      "original_path": "rlgraph/tests/agent_functionality/test_base_agent_functionality.py",
      "size": 4025,
      "alphanum_fraction": 0.6722981366,
      "line_count": 104,
      "character_count": 4025
    },
    {
      "file": "test_impala_agent_long_task_learning.py",
      "original_path": "rlgraph/tests/agent_learning/long_tasks/test_impala_agent_long_task_learning.py",
      "size": 3015,
      "alphanum_fraction": 0.6543946932,
      "line_count": 84,
      "character_count": 3015
    },
    {
      "file": "test_string_layers.py",
      "original_path": "rlgraph/tests/components/test_string_layers.py",
      "size": 4947,
      "alphanum_fraction": 0.5886395795,
      "line_count": 116,
      "character_count": 4947
    }
  ]
}