{
  "repo_name": "Wlgen/force-riscv",
  "stars": 111,
  "license": [
    "Apache-2.0"
  ],
  "first_star_date": null,
  "total_files": 5,
  "files": [
    {
      "file": "State_force.py",
      "original_path": "tests/riscv/APIs/State_force.py",
      "size": 2908,
      "alphanum_fraction": 0.7252407153,
      "line_count": 75,
      "character_count": 2908
    },
    {
      "file": "collections.py",
      "original_path": "utils/regression/common/collections.py",
      "size": 3832,
      "alphanum_fraction": 0.6255219207,
      "line_count": 152,
      "character_count": 3832
    },
    {
      "file": "create_diff.py",
      "original_path": "utils/svn/create_diff.py",
      "size": 4108,
      "alphanum_fraction": 0.63218111,
      "line_count": 146,
      "character_count": 4108
    },
    {
      "file": "state_transition_simple_force.py",
      "original_path": "examples/tutorial/state_transition_simple_force.py",
      "size": 3270,
      "alphanum_fraction": 0.6633027523,
      "line_count": 91,
      "character_count": 3270
    },
    {
      "file": "tool_executor.py",
      "original_path": "utils/regression/executors/tool_executor.py",
      "size": 2079,
      "alphanum_fraction": 0.7113997114,
      "line_count": 61,
      "character_count": 2079
    }
  ]
}