{
  "repo_name": "cromulencellc/asn1tools",
  "stars": 198,
  "license": [
    "MIT"
  ],
  "first_star_date": null,
  "total_files": 5,
  "files": [
    {
      "file": "test_per.py",
      "original_path": "tests/test_per.py",
      "size": 88149,
      "alphanum_fraction": 0.3478995791,
      "line_count": 2221,
      "character_count": 88149
    },
    {
      "file": "compile_methods.py",
      "original_path": "examples/benchmarks/compile_methods.py",
      "size": 4686,
      "alphanum_fraction": 0.6163038839,
      "line_count": 177,
      "character_count": 4686
    },
    {
      "file": "test_command_line.py",
      "original_path": "tests/test_command_line.py",
      "size": 30871,
      "alphanum_fraction": 0.4351980823,
      "line_count": 855,
      "character_count": 30871
    },
    {
      "file": "__init__.py",
      "original_path": "asn1tools/__init__.py",
      "size": 14769,
      "alphanum_fraction": 0.5612431444,
      "line_count": 438,
      "character_count": 14769
    },
    {
      "file": "uper.py",
      "original_path": "asn1tools/source/rust/uper.py",
      "size": 25253,
      "alphanum_fraction": 0.5069100701,
      "line_count": 781,
      "character_count": 25253
    }
  ]
}