{
  "repo_name": "onelsonic/armory",
  "stars": 2583,
  "license": [
    "Zlib"
  ],
  "first_star_date": null,
  "total_files": 5,
  "files": [
    {
      "file": "encoding.py",
      "original_path": "blender/arm/lightmapper/utility/encoding.py",
      "size": 20293,
      "alphanum_fraction": 0.5888237323,
      "line_count": 644,
      "character_count": 20293
    },
    {
      "file": "armpack.py",
      "original_path": "blender/arm/lib/armpack.py",
      "size": 5638,
      "alphanum_fraction": 0.5718339837,
      "line_count": 165,
      "character_count": 5638
    },
    {
      "file": "make_renderpath.py",
      "original_path": "blender/arm/make_renderpath.py",
      "size": 15790,
      "alphanum_fraction": 0.6366054465,
      "line_count": 400,
      "character_count": 15790
    },
    {
      "file": "cycles.py",
      "original_path": "blender/arm/material/cycles.py",
      "size": 33353,
      "alphanum_fraction": 0.6370341499,
      "line_count": 915,
      "character_count": 33353
    },
    {
      "file": "prepare.py",
      "original_path": "blender/arm/lightmapper/utility/cycles/prepare.py",
      "size": 27106,
      "alphanum_fraction": 0.55212868,
      "line_count": 616,
      "character_count": 27106
    }
  ]
}