{
  "repo_name": "nzlosh/yaql",
  "stars": 112,
  "license": [
    "Apache-2.0"
  ],
  "first_star_date": null,
  "total_files": 5,
  "files": [
    {
      "file": "test_common.py",
      "original_path": "yaql/tests/test_common.py",
      "size": 3068,
      "alphanum_fraction": 0.6222294654,
      "line_count": 79,
      "character_count": 3068
    },
    {
      "file": "conf.py",
      "original_path": "doc/source/conf.py",
      "size": 2590,
      "alphanum_fraction": 0.7073359073,
      "line_count": 77,
      "character_count": 2590
    },
    {
      "file": "strings.py",
      "original_path": "yaql/standard_library/strings.py",
      "size": 29835,
      "alphanum_fraction": 0.6547008547,
      "line_count": 1064,
      "character_count": 29835
    },
    {
      "file": "specs.py",
      "original_path": "yaql/language/specs.py",
      "size": 17781,
      "alphanum_fraction": 0.5908554075,
      "line_count": 469,
      "character_count": 17781
    },
    {
      "file": "test_boolean.py",
      "original_path": "yaql/tests/test_boolean.py",
      "size": 2566,
      "alphanum_fraction": 0.6488698363,
      "line_count": 62,
      "character_count": 2566
    }
  ]
}